ML4HD_Labs/Lab_1/Lab_1_utils.py
ML4HD_Labs/Lab_2/Lab_2_datasets.py
ML4HD_Labs/Lab_2/Lab_2_utils.py
ml4hd_labs-0.0.7.dist-info/METADATA
ml4hd_labs-0.0.7.dist-info/WHEEL
ml4hd_labs-0.0.7.dist-info/top_level.txt
ml4hd_labs-0.0.7.dist-info/RECORD
