Metadata-Version: 2.4
Name: ML4HD_Labs
Version: 0.0.7
Summary: Helper functions and utilities for ML4HD labs
Requires-Python: >=3.8
Requires-Dist: matplotlib>=3.7.5
Requires-Dist: numpy>=1.24.4
Requires-Dist: opencv-python>=4.11.0.86
Requires-Dist: tensorflow>=2.11.1
Requires-Dist: tqdm>=4.67.1
